pennylane_cirq/__init__.py
pennylane_cirq/_version.py
pennylane_cirq/cirq_device.py
pennylane_cirq/cirq_operation.py
pennylane_cirq/ops.py
pennylane_cirq/pasqal_device.py
pennylane_cirq/qsim_device.py
pennylane_cirq/simulator_device.py
pennylane_cirq-0.43.0.dist-info/licenses/LICENSE
pennylane_cirq-0.43.0.dist-info/METADATA
pennylane_cirq-0.43.0.dist-info/WHEEL
pennylane_cirq-0.43.0.dist-info/entry_points.txt
pennylane_cirq-0.43.0.dist-info/top_level.txt
pennylane_cirq-0.43.0.dist-info/RECORD
